jupyter_notebook_renderer/__init__.py
jupyter_notebook_renderer/custom_exception.py
jupyter_notebook_renderer/logger.py
jupyter_notebook_renderer/youtube.py
jupyter_notebook_renderer-0.0.2.dist-info/METADATA
jupyter_notebook_renderer-0.0.2.dist-info/WHEEL
jupyter_notebook_renderer-0.0.2.dist-info/top_level.txt
jupyter_notebook_renderer-0.0.2.dist-info/RECORD
