Metadata-Version: 2.1
Name: jupyter_notebook_renderer
Version: 0.0.2
Summary: A small python package
Home-page: https://github.com/HimanshuChoudhary3004/Jupyter-Notebook-renderer
Author: HimanshuChoudhary3004
Author-email: hchoudhary525@gmail.com
License: MIT
Project-URL: Bug Tracker, https://github.com/HimanshuChoudhary3004/Jupyter-Notebook-renderer/issues
Classifier: Programming Language :: Python :: 3.10
Classifier: Programming Language :: Python :: 3.11
Classifier: Programming Language :: Python :: 3.12
Requires-Python: >3.7
Requires-Dist: ensure
Requires-Dist: py-youtube
Provides-Extra: testing
Requires-Dist: pytest >=7.1.3 ; extra == 'testing'
Requires-Dist: mypy >=1.8.0 ; extra == 'testing'
Requires-Dist: flake8 >=5.0.4 ; extra == 'testing'
Requires-Dist: tox >=3.25.1 ; extra == 'testing'
Requires-Dist: black >=22.8.0 ; extra == 'testing'
